setup.py
ema_distributions/Binomialdistribution.py
ema_distributions/Gaussiandistribution.py
ema_distributions/Generaldistribution.py
ema_distributions/__init__.py
ema_distributions.egg-info/PKG-INFO
ema_distributions.egg-info/SOURCES.txt
ema_distributions.egg-info/dependency_links.txt
ema_distributions.egg-info/not-zip-safe
ema_distributions.egg-info/top_level.txt